pyionics/__init__.py
pyionics/base.py
pyionics/keyData/property_idsets.csv
pyionics/keyData/smiles.csv
pyionics-0.4.3.dist-info/METADATA
pyionics-0.4.3.dist-info/WHEEL
pyionics-0.4.3.dist-info/top_level.txt
pyionics-0.4.3.dist-info/RECORD
