Metadata-Version: 2.1
Name: pyionics
Version: 0.4.3
Author: KamranHeydarov
Requires-Dist: pandas <3.0.0,>=1.3.0
Requires-Dist: requests <3.0.0,>=2.25.0
Requires-Dist: tqdm <5.0.0,>=4.60.0
